<?xml version='1.0' encoding='utf-8' standalone='no'?>
<?xml-stylesheet type='text/xsl' href='StandrdGraphsStyle.xsl'?><Assessment xmlns:xsi='http://www.w3.org/2001/XMLSchema-instance' xsi:noNamespaceSchemaLocation='ICES_Standard_Graphs.xsd'><FishStock>nop-34-oct</FishStock><AssessmentYear>2016</AssessmentYear><Blim>39450</Blim><Bpa>65000</Bpa><RecruitmentAge>0</RecruitmentAge><FAge>1-2</FAge><UnitsWeigths>tonnes</UnitsWeigths><UnitsRecruits>thousands</UnitsRecruits><FishData><Year>1984</Year><Low_Recruitment>23149000</Low_Recruitment><Recruitment>38844000</Recruitment><High_Recruitment>65180000</High_Recruitment><Low_TBiomass>305683</Low_TBiomass><TBiomass>495278</TBiomass><High_TBiomass>684873</High_TBiomass><Low_SSB>48878</Low_SSB><SSB>100131</SSB><High_SSB>151384</High_SSB><Catches>376555</Catches><Low_F>0.928</Low_F><F>1.418</F><High_F>2.168</High_F></FishData><FishData><Year>1985</Year><Low_Recruitment>15481000</Low_Recruitment><Recruitment>25676000</Recruitment><High_Recruitment>42587000</High_Recruitment><Low_TBiomass>168725</Low_TBiomass><TBiomass>274882</TBiomass><High_TBiomass>381039</High_TBiomass><Low_SSB>23905</Low_SSB><SSB>51338</SSB><High_SSB>78770</High_SSB><Catches>227482</Catches><Low_F>0.892</Low_F><F>1.415</F><High_F>2.245</High_F></FishData><FishData><Year>1986</Year><Low_Recruitment>29313000</Low_Recruitment><Recruitment>51094000</Recruitment><High_Recruitment>89062000</High_Recruitment><Low_TBiomass>207131</Low_TBiomass><TBiomass>351039</TBiomass><High_TBiomass>494948</High_TBiomass><Low_SSB>17166</Low_SSB><SSB>36352</SSB><High_SSB>55538</High_SSB><Catches>180508</Catches><Low_F>0.6</Low_F><F>0.987</F><High_F>1.623</High_F></FishData><FishData><Year>1987</Year><Low_Recruitment>6553000</Low_Recruitment><Recruitment>11337000</Recruitment><High_Recruitment>19614000</High_Recruitment><Low_TBiomass>170174</Low_TBiomass><TBiomass>304279</TBiomass><High_TBiomass>438385</High_TBiomass><Low_SSB>32401</Low_SSB><SSB>63482</SSB><High_SSB>94563</High_SSB><Catches>148894</Catches><Low_F>0.574</Low_F><F>1.016</F><High_F>1.798</High_F></FishData><FishData><Year>1988</Year><Low_Recruitment>25779000</Low_Recruitment><Recruitment>42853000</Recruitment><High_Recruitment>71236000</High_Recruitment><Low_TBiomass>169952</Low_TBiomass><TBiomass>289585</TBiomass><High_TBiomass>409218</High_TBiomass><Low_SSB>19790</Low_SSB><SSB>53014</SSB><High_SSB>86237</High_SSB><Catches>109295</Catches><Low_F>0.388</Low_F><F>0.642</F><High_F>1.063</High_F></FishData><FishData><Year>1989</Year><Low_Recruitment>27462000</Low_Recruitment><Recruitment>45617000</Recruitment><High_Recruitment>75774000</High_Recruitment><Low_TBiomass>254370</Low_TBiomass><TBiomass>412689</TBiomass><High_TBiomass>571009</High_TBiomass><Low_SSB>27659</Low_SSB><SSB>54411</SSB><High_SSB>81164</High_SSB><Catches>166559</Catches><Low_F>0.443</Low_F><F>0.745</F><High_F>1.253</High_F></FishData><FishData><Year>1990</Year><Low_Recruitment>34362000</Low_Recruitment><Recruitment>58374000</Recruitment><High_Recruitment>99166000</High_Recruitment><Low_TBiomass>296853</Low_TBiomass><TBiomass>494792</TBiomass><High_TBiomass>692731</High_TBiomass><Low_SSB>35381</Low_SSB><SSB>71577</SSB><High_SSB>107773</High_SSB><Catches>139095</Catches><Low_F>0.415</Low_F><F>0.691</F><High_F>1.152</High_F></FishData><FishData><Year>1991</Year><Low_Recruitment>54570000</Low_Recruitment><Recruitment>90594000</Recruitment><High_Recruitment>150398000</High_Recruitment><Low_TBiomass>434918</Low_TBiomass><TBiomass>720850</TBiomass><High_TBiomass>1006783</High_TBiomass><Low_SSB>46218</Low_SSB><SSB>93947</SSB><High_SSB>141675</High_SSB><Catches>190406</Catches><Low_F>0.381</Low_F><F>0.634</F><High_F>1.053</High_F></FishData><FishData><Year>1992</Year><Low_Recruitment>29441000</Low_Recruitment><Recruitment>48906000</Recruitment><High_Recruitment>81239000</High_Recruitment><Low_TBiomass>408344</Low_TBiomass><TBiomass>693374</TBiomass><High_TBiomass>978404</High_TBiomass><Low_SSB>71218</Low_SSB><SSB>144778</SSB><High_SSB>218338</High_SSB><Catches>302490</Catches><Low_F>0.372</Low_F><F>0.613</F><High_F>1.011</High_F></FishData><FishData><Year>1993</Year><Low_Recruitment>24092000</Low_Recruitment><Recruitment>41613000</Recruitment><High_Recruitment>71876000</High_Recruitment><Low_TBiomass>264681</Low_TBiomass><TBiomass>467626</TBiomass><High_TBiomass>670572</High_TBiomass><Low_SSB>49399</Low_SSB><SSB>118572</SSB><High_SSB>187745</High_SSB><Catches>181265</Catches><Low_F>0.378</Low_F><F>0.703</F><High_F>1.308</High_F></FishData><FishData><Year>1994</Year><Low_Recruitment>70026000</Low_Recruitment><Recruitment>120915000</Recruitment><High_Recruitment>208785000</High_Recruitment><Low_TBiomass>398251</Low_TBiomass><TBiomass>769335</TBiomass><High_TBiomass>1140420</High_TBiomass><Low_SSB>30377</Low_SSB><SSB>82607</SSB><High_SSB>134838</High_SSB><Catches>183585</Catches><Low_F>0.311</Low_F><F>0.563</F><High_F>1.02</High_F></FishData><FishData><Year>1995</Year><Low_Recruitment>27507000</Low_Recruitment><Recruitment>48852000</Recruitment><High_Recruitment>86762000</High_Recruitment><Low_TBiomass>436633</Low_TBiomass><TBiomass>864630</TBiomass><High_TBiomass>1292627</High_TBiomass><Low_SSB>75028</Low_SSB><SSB>168942</SSB><High_SSB>262855</High_SSB><Catches>231772</Catches><Low_F>0.207</Low_F><F>0.386</F><High_F>0.722</High_F></FishData><FishData><Year>1996</Year><Low_Recruitment>57178000</Low_Recruitment><Recruitment>99835000</Recruitment><High_Recruitment>174314000</High_Recruitment><Low_TBiomass>421058</Low_TBiomass><TBiomass>835261</TBiomass><High_TBiomass>1249463</High_TBiomass><Low_SSB>67265</Low_SSB><SSB>198664</SSB><High_SSB>330063</High_SSB><Catches>156079</Catches><Low_F>0.182</Low_F><F>0.349</F><High_F>0.671</High_F></FishData><FishData><Year>1997</Year><Low_Recruitment>12443000</Low_Recruitment><Recruitment>21995000</Recruitment><High_Recruitment>38878000</High_Recruitment><Low_TBiomass>340039</Low_TBiomass><TBiomass>717041</TBiomass><High_TBiomass>1094044</High_TBiomass><Low_SSB>79040</Low_SSB><SSB>195997</SSB><High_SSB>312953</High_SSB><Catches>156937</Catches><Low_F>0.176</Low_F><F>0.344</F><High_F>0.673</High_F></FishData><FishData><Year>1998</Year><Low_Recruitment>21894000</Low_Recruitment><Recruitment>37909000</Recruitment><High_Recruitment>65637000</High_Recruitment><Low_TBiomass>216569</Low_TBiomass><TBiomass>446004</TBiomass><High_TBiomass>675438</High_TBiomass><Low_SSB>58212</Low_SSB><SSB>178851</SSB><High_SSB>299490</High_SSB><Catches>75034</Catches><Low_F>0.159</Low_F><F>0.303</F><High_F>0.577</High_F></FishData><FishData><Year>1999</Year><Low_Recruitment>49643000</Low_Recruitment><Recruitment>86098000</Recruitment><High_Recruitment>149323000</High_Recruitment><Low_TBiomass>339089</Low_TBiomass><TBiomass>664778</TBiomass><High_TBiomass>990467</High_TBiomass><Low_SSB>37486</Low_SSB><SSB>103686</SSB><High_SSB>169885</High_SSB><Catches>92302</Catches><Low_F>0.189</Low_F><F>0.366</F><High_F>0.708</High_F></FishData><FishData><Year>2000</Year><Low_Recruitment>12940000</Low_Recruitment><Recruitment>22880000</Recruitment><High_Recruitment>40457000</High_Recruitment><Low_TBiomass>313148</Low_TBiomass><TBiomass>667480</TBiomass><High_TBiomass>1021813</High_TBiomass><Low_SSB>70648</Low_SSB><SSB>168826</SSB><High_SSB>267004</High_SSB><Catches>184970</Catches><Low_F>0.172</Low_F><F>0.343</F><High_F>0.685</High_F></FishData><FishData><Year>2001</Year><Low_Recruitment>13096000</Low_Recruitment><Recruitment>22797000</Recruitment><High_Recruitment>39683000</High_Recruitment><Low_TBiomass>172994</Low_TBiomass><TBiomass>367481</TBiomass><High_TBiomass>561968</High_TBiomass><Low_SSB>58786</Low_SSB><SSB>170115</SSB><High_SSB>281444</High_SSB><Catches>64373</Catches><Low_F>0.127</Low_F><F>0.258</F><High_F>0.522</High_F></FishData><FishData><Year>2002</Year><Low_Recruitment>9450000</Low_Recruitment><Recruitment>18137000</Recruitment><High_Recruitment>34809000</High_Recruitment><Low_TBiomass>115705</Low_TBiomass><TBiomass>258874</TBiomass><High_TBiomass>402043</High_TBiomass><Low_SSB>27360</Low_SSB><SSB>83413</SSB><High_SSB>139466</High_SSB><Catches>77108</Catches><Low_F>0.174</Low_F><F>0.377</F><High_F>0.817</High_F></FishData><FishData><Year>2003</Year><Low_Recruitment>4401000</Low_Recruitment><Recruitment>8126000</Recruitment><High_Recruitment>15002000</High_Recruitment><Low_TBiomass>70306</Low_TBiomass><TBiomass>160251</TBiomass><High_TBiomass>250197</High_TBiomass><Low_SSB>18902</Low_SSB><SSB>57428</SSB><High_SSB>95954</High_SSB><Catches>24647</Catches><Low_F>0.109</Low_F><F>0.245</F><High_F>0.548</High_F></FishData><FishData><Year>2004</Year><Low_Recruitment>4288000</Low_Recruitment><Recruitment>7691000</Recruitment><High_Recruitment>13793000</High_Recruitment><Low_TBiomass>48796</Low_TBiomass><TBiomass>110181</TBiomass><High_TBiomass>171565</High_TBiomass><Low_SSB>13536</Low_SSB><SSB>41512</SSB><High_SSB>69488</High_SSB><Catches>13487</Catches><Low_F>0.085</Low_F><F>0.203</F><High_F>0.484</High_F></FishData><FishData><Year>2005</Year><Low_Recruitment>16007000</Low_Recruitment><Recruitment>28746000</Recruitment><High_Recruitment>51623000</High_Recruitment><Low_TBiomass>92274</Low_TBiomass><TBiomass>194782</TBiomass><High_TBiomass>297289</High_TBiomass><Low_SSB>11647</Low_SSB><SSB>30355</SSB><High_SSB>49063</High_SSB><Catches>42</Catches><Low_F>0</Low_F><F>0</F><High_F>0.001</High_F></FishData><FishData><Year>2006</Year><Low_Recruitment>11171000</Low_Recruitment><Recruitment>20372000</Recruitment><High_Recruitment>37152000</High_Recruitment><Low_TBiomass>127368</Low_TBiomass><TBiomass>272418</TBiomass><High_TBiomass>417469</High_TBiomass><Low_SSB>22406</Low_SSB><SSB>51615</SSB><High_SSB>80824</High_SSB><Catches>46553</Catches><Low_F>0.126</Low_F><F>0.318</F><High_F>0.803</High_F></FishData><FishData><Year>2007</Year><Low_Recruitment>16954000</Low_Recruitment><Recruitment>30789000</Recruitment><High_Recruitment>55913000</High_Recruitment><Low_TBiomass>139936</Low_TBiomass><TBiomass>306532</TBiomass><High_TBiomass>473128</High_TBiomass><Low_SSB>27416</Low_SSB><SSB>75342</SSB><High_SSB>123267</High_SSB><Catches>5796</Catches><Low_F>0.016</Low_F><F>0.035</F><High_F>0.074</High_F></FishData><FishData><Year>2008</Year><Low_Recruitment>25888000</Low_Recruitment><Recruitment>49378000</Recruitment><High_Recruitment>94180000</High_Recruitment><Low_TBiomass>217038</Low_TBiomass><TBiomass>462938</TBiomass><High_TBiomass>708837</High_TBiomass><Low_SSB>36351</Low_SSB><SSB>89830</SSB><High_SSB>143310</High_SSB><Catches>34844</Catches><Low_F>0.033</Low_F><F>0.07</F><High_F>0.148</High_F></FishData><FishData><Year>2009</Year><Low_Recruitment>38391000</Low_Recruitment><Recruitment>69386000</Recruitment><High_Recruitment>125403000</High_Recruitment><Low_TBiomass>323187</Low_TBiomass><TBiomass>697485</TBiomass><High_TBiomass>1071784</High_TBiomass><Low_SSB>51985</Low_SSB><SSB>129363</SSB><High_SSB>206740</High_SSB><Catches>45813</Catches><Low_F>0.053</Low_F><F>0.12</F><High_F>0.274</High_F></FishData><FishData><Year>2010</Year><Low_Recruitment>3720000</Low_Recruitment><Recruitment>6839000</Recruitment><High_Recruitment>12574000</High_Recruitment><Low_TBiomass>230028</Low_TBiomass><TBiomass>559616</TBiomass><High_TBiomass>889204</High_TBiomass><Low_SSB>73398</Low_SSB><SSB>206932</SSB><High_SSB>340465</High_SSB><Catches>131078</Catches><Low_F>0.061</Low_F><F>0.132</F><High_F>0.285</High_F></FishData><FishData><Year>2011</Year><Low_Recruitment>6484000</Low_Recruitment><Recruitment>11537000</Recruitment><High_Recruitment>20526000</High_Recruitment><Low_TBiomass>108514</Low_TBiomass><TBiomass>254174</TBiomass><High_TBiomass>399835</High_TBiomass><Low_SSB>59832</Low_SSB><SSB>170466</SSB><High_SSB>281099</High_SSB><Catches>6843</Catches><Low_F>0.031</Low_F><F>0.069</F><High_F>0.154</High_F></FishData><FishData><Year>2012</Year><Low_Recruitment>28090000</Low_Recruitment><Recruitment>51466000</Recruitment><High_Recruitment>94295000</High_Recruitment><Low_TBiomass>162540</Low_TBiomass><TBiomass>354463</TBiomass><High_TBiomass>546386</High_TBiomass><Low_SSB>24943</Low_SSB><SSB>68083</SSB><High_SSB>111223</High_SSB><Catches>26947</Catches><Low_F>0.083</Low_F><F>0.197</F><High_F>0.469</High_F></FishData><FishData><Year>2013</Year><Low_Recruitment>7640000</Low_Recruitment><Recruitment>14086000</Recruitment><High_Recruitment>25972000</High_Recruitment><Low_TBiomass>173843</Low_TBiomass><TBiomass>361436</TBiomass><High_TBiomass>549028</High_TBiomass><Low_SSB>37246</Low_SSB><SSB>83805</SSB><High_SSB>130365</High_SSB><Catches>82109</Catches><Low_F>0.142</Low_F><F>0.366</F><High_F>0.943</High_F></FishData><FishData><Year>2014</Year><Low_Recruitment>42895000</Low_Recruitment><Recruitment>84971000</Recruitment><High_Recruitment>168321000</High_Recruitment><Low_TBiomass>209944</Low_TBiomass><TBiomass>510280</TBiomass><High_TBiomass>810615</High_TBiomass><Low_SSB>23932</Low_SSB><SSB>79516</SSB><High_SSB>135100</High_SSB><Catches>44164</Catches><Low_F>0.12</Low_F><F>0.298</F><High_F>0.741</High_F></FishData><FishData><Year>2015</Year><Low_Recruitment>24839000</Low_Recruitment><Recruitment>46995000</Recruitment><High_Recruitment>88912000</High_Recruitment><Low_TBiomass>272133</Low_TBiomass><TBiomass>637407</TBiomass><High_TBiomass>1002682</High_TBiomass><Low_SSB>38444</Low_SSB><SSB>109857</SSB><High_SSB>181270</High_SSB><Catches>57417</Catches><Low_F>0.102</Low_F><F>0.273</F><High_F>0.729</High_F></FishData><FishData><Year>2016</Year><Low_Recruitment>40459000</Low_Recruitment><Recruitment>96296000</Recruitment><High_Recruitment>229189000</High_Recruitment><Low_TBiomass>242772</Low_TBiomass><TBiomass>659162</TBiomass><High_TBiomass>1075552</High_TBiomass><Low_SSB>42388</Low_SSB><SSB>166849</SSB><High_SSB>291310</High_SSB><Catches>25286</Catches></FishData></Assessment>